ipy_dict_hierarchy/__init__.py
ipy_dict_hierarchy/hierarchical_pprint.py
ipy_dict_hierarchy/tab_completion_benedict.py
ipy_dict_hierarchy/tab_completion_dict.py
ipy_dict_hierarchy-0.0.2.dist-info/LICENSE
ipy_dict_hierarchy-0.0.2.dist-info/WHEEL
ipy_dict_hierarchy-0.0.2.dist-info/METADATA
ipy_dict_hierarchy-0.0.2.dist-info/RECORD
