Metadata-Version: 2.1
Name: ipy_dict_hierarchy
Version: 0.0.2
Summary: IPython Extension to pretty print nested dicts
Author-email: "F. Paul Spitzner" <paul.spitzner@ds.mpg.de>
Requires-Python: >=3.7
Classifier: Programming Language :: Python :: 3
Classifier: License :: OSI Approved :: MIT License
Classifier: Operating System :: OS Independent
Classifier: Framework :: IPython
Classifier: Topic :: Utilities
